automation_editor/__init__.py
automation_editor/__main__.py
automation_editor/automation_editor_ui/__init__.py
automation_editor/automation_editor_ui/editor_main/__init__.py
automation_editor/automation_editor_ui/editor_main/main_ui.py
automation_editor/automation_editor_ui/extend_multi_language/__init__.py
automation_editor/automation_editor_ui/extend_multi_language/extend_english.py
automation_editor/automation_editor_ui/extend_multi_language/extend_traditional_chinese.py
automation_editor/automation_editor_ui/extend_multi_language/update_language_dict.py
automation_editor/automation_editor_ui/menu/__init__.py
automation_editor/automation_editor_ui/menu/build_menubar.py
automation_editor/automation_editor_ui/menu/menu_utils.py
automation_editor/automation_editor_ui/menu/automation_menu/__init__.py
automation_editor/automation_editor_ui/menu/automation_menu/api_testka_menu/__init__.py
automation_editor/automation_editor_ui/menu/automation_menu/api_testka_menu/build_api_testka_menu.py
automation_editor/automation_editor_ui/menu/automation_menu/auto_control_menu/__init__.py
automation_editor/automation_editor_ui/menu/automation_menu/auto_control_menu/build_autocontrol_menu.py
automation_editor/automation_editor_ui/menu/automation_menu/automation_file_menu/__init__.py
automation_editor/automation_editor_ui/menu/automation_menu/automation_file_menu/build_automation_file_menu.py
automation_editor/automation_editor_ui/menu/automation_menu/load_density_menu/__init__.py
automation_editor/automation_editor_ui/menu/automation_menu/load_density_menu/build_load_density_menu.py
automation_editor/automation_editor_ui/menu/automation_menu/mail_thunder_menu/__init__.py
automation_editor/automation_editor_ui/menu/automation_menu/mail_thunder_menu/build_mail_thunder_menu.py
automation_editor/automation_editor_ui/menu/automation_menu/web_runner_menu/__init__.py
automation_editor/automation_editor_ui/menu/automation_menu/web_runner_menu/build_webrunner_menu.py
automation_editor_dev-0.0.34.dist-info/LICENSE
automation_editor_dev-0.0.34.dist-info/METADATA
automation_editor_dev-0.0.34.dist-info/WHEEL
automation_editor_dev-0.0.34.dist-info/top_level.txt
automation_editor_dev-0.0.34.dist-info/RECORD
