Metadata-Version: 2.1
Name: automation_editor_dev
Version: 0.0.34
Summary: AutomationEditor for multi automation
Author-email: JE-Chen <jechenmailman@gmail.com>
License: MIT
Project-URL: Homepage, https://github.com/Intergration-Automation-Testing/AutomationEditor
Project-URL: Code, https://github.com/Intergration-Automation-Testing/AutomationEditor
Classifier: Programming Language :: Python :: 3.9
Classifier: Development Status :: 2 - Pre-Alpha
Classifier: Environment :: Win32 (MS Windows)
Classifier: Environment :: MacOS X
Classifier: Environment :: X11 Applications
Classifier: License :: OSI Approved :: MIT License
Classifier: Operating System :: OS Independent
Requires-Python: >=3.9
License-File: LICENSE
Requires-Dist: je-editor
Requires-Dist: je-auto-control
Requires-Dist: je-web-runner
Requires-Dist: je-load-density
Requires-Dist: je-api-testka
Requires-Dist: je-mail-thunder
Requires-Dist: automation-file
